[
    {
        "brand":  "توركی",
        "name":  "دۆشەكی ڕۆیاڵ1*2",
        "ID":  1,
        "Item_type":  ""
    },
    {
        "brand":  "",
        "name":  "دۆشەكی ڕۆیاڵ120*2",
        "ID":  2,
        "Item_type":  ""
    },
    {
        "brand":  "",
        "name":  "دۆشەكی ڕۆیاڵ160*2",
        "ID":  3,
        "Item_type":  ""
    },
    {
        "brand":  "",
        "name":  "دۆشەكی ڕۆیاڵ180*2",
        "ID":  4,
        "Item_type":  ""
    },
    {
        "brand":  "",
        "name":  "دۆشەكی ڕؤیاڵ 2*2",
        "ID":  5,
        "Item_type":  ""
    },
    {
        "brand":  "",
        "name":  "دۆشەكی بێتا90*190",
        "ID":  6,
        "Item_type":  ""
    },
    {
        "brand":  "",
        "name":  "دۆشەكی بێتا90*2",
        "ID":  7,
        "Item_type":  ""
    },
    {
        "brand":  "",
        "name":  "دۆشەكی بێتا1*2",
        "ID":  8,
        "Item_type":  ""
    },
    {
        "brand":  "",
        "name":  "دۆشەكی بێتا120*2",
        "ID":  9,
        "Item_type":  ""
    },
    {
        "brand":  "",
        "name":  "دۆشەكی بێتا150*2",
        "ID":  10,
        "Item_type":  ""
    },
    {
        "brand":  "",
        "name":  "دۆشەكی بێتا160*2",
        "ID":  11,
        "Item_type":  ""
    },
    {
        "brand":  "",
        "name":  "دۆشەكی بێتا180*2",
        "ID":  12,
        "Item_type":  ""
    },
    {
        "brand":  "",
        "name":  "دۆشەكی بێتا2*2",
        "ID":  13,
        "Item_type":  ""
    },
    {
        "brand":  "",
        "name":  "دۆشەكی پاڕادایس1*2",
        "ID":  14,
        "Item_type":  ""
    },
    {
        "brand":  "",
        "name":  "دۆشەكی پاڕادایس120*2",
        "ID":  15,
        "Item_type":  ""
    },
    {
        "brand":  "",
        "name":  "دۆشەكی پاڕادایس160*2",
        "ID":  16,
        "Item_type":  ""
    },
    {
        "brand":  "",
        "name":  "دۆشەكی پاڕادایس180*2",
        "ID":  17,
        "Item_type":  ""
    },
    {
        "brand":  "",
        "name":  "دۆشەكی پاڕادایس2*2",
        "ID":  18,
        "Item_type":  ""
    },
    {
        "brand":  "",
        "name":  "دۆشەكی كڵاود 1*2",
        "ID":  19,
        "Item_type":  ""
    },
    {
        "brand":  "",
        "name":  "دۆشەكی كڵاود120*2",
        "ID":  20,
        "Item_type":  ""
    },
    {
        "brand":  "",
        "name":  "دۆشەكی كڵاود150*2",
        "ID":  21,
        "Item_type":  ""
    },
    {
        "brand":  "",
        "name":  "دۆشەكی كڵاود160*2",
        "ID":  22,
        "Item_type":  ""
    },
    {
        "brand":  "",
        "name":  "دۆشەكی كڵاود180*2",
        "ID":  23,
        "Item_type":  ""
    },
    {
        "brand":  "",
        "name":  "دۆشەكی كڵاود2*2",
        "ID":  24,
        "Item_type":  ""
    },
    {
        "brand":  "",
        "name":  "دۆشەكی ستاره 90*190",
        "ID":  25,
        "Item_type":  ""
    },
    {
        "brand":  "",
        "name":  " دۆشەكی ستاره90*2",
        "ID":  26,
        "Item_type":  ""
    },
    {
        "brand":  "",
        "name":  "دۆشەكی ستاره1*2",
        "ID":  27,
        "Item_type":  ""
    },
    {
        "brand":  "",
        "name":  "دۆشەكی ستارە120*2",
        "ID":  28,
        "Item_type":  ""
    },
    {
        "brand":  "",
        "name":  "دۆشەكی بێتریس1*2",
        "ID":  29,
        "Item_type":  ""
    },
    {
        "brand":  "",
        "name":  "دۆشەكی بێتریس120*2",
        "ID":  30,
        "Item_type":  ""
    },
    {
        "brand":  "",
        "name":  "دۆشەكی تۆپ كوالێتی120*2",
        "ID":  31,
        "Item_type":  ""
    },
    {
        "brand":  "",
        "name":  "دۆشەكی تۆپ كوالێتی150*2",
        "ID":  32,
        "Item_type":  ""
    },
    {
        "brand":  "",
        "name":  "دۆشەكی تۆپ كوالێتی160*2",
        "ID":  33,
        "Item_type":  ""
    },
    {
        "brand":  "",
        "name":  "دۆشەكی تۆپ كوالێتی180*2",
        "ID":  34,
        "Item_type":  ""
    },
    {
        "brand":  "",
        "name":  "دۆشەكی تۆپ كوالێتی2*2",
        "ID":  35,
        "Item_type":  ""
    },
    {
        "brand":  "",
        "name":  "دۆشەكی ستایل160*2",
        "ID":  36,
        "Item_type":  ""
    },
    {
        "brand":  "",
        "name":  "دۆشەكی ستایل 180*2",
        "ID":  37,
        "Item_type":  ""
    },
    {
        "brand":  "",
        "name":  "دۆشەكی ستایل 2*2",
        "ID":  38,
        "Item_type":  ""
    },
    {
        "brand":  "",
        "name":  "دۆشەكی بێست160*2",
        "ID":  39,
        "Item_type":  ""
    },
    {
        "brand":  "",
        "name":  "دۆشەكی بێست 180*2",
        "ID":  40,
        "Item_type":  ""
    },
    {
        "brand":  "",
        "name":  "دۆشەكی بێست2*2",
        "ID":  41,
        "Item_type":  ""
    },
    {
        "brand":  "",
        "name":  "دۆشەكی ڤیسكۆ ئەنەتۆمی 160*2",
        "ID":  42,
        "Item_type":  ""
    },
    {
        "brand":  "",
        "name":  "دۆشەكی ڤیسكۆ ئەنەتۆمی 180*2",
        "ID":  43,
        "Item_type":  ""
    },
    {
        "brand":  "",
        "name":  "دۆشەكی ڤیسكۆ ئەنەتۆمی 2*2",
        "ID":  44,
        "Item_type":  ""
    },
    {
        "brand":  "",
        "name":  "دۆشەكی ماتمازێل 160*2",
        "ID":  45,
        "Item_type":  ""
    },
    {
        "brand":  "",
        "name":  "دۆشەكی ماتمازێل180*2",
        "ID":  46,
        "Item_type":  ""
    },
    {
        "brand":  "",
        "name":  "دۆشەكی دایمۆند 160*2",
        "ID":  47,
        "Item_type":  ""
    },
    {
        "brand":  "",
        "name":  "دۆشەكی دایمۆند180*2",
        "ID":  48,
        "Item_type":  ""
    },
    {
        "brand":  "",
        "name":  "دۆشەكی دایمۆند2*2",
        "ID":  49,
        "Item_type":  ""
    },
    {
        "brand":  "",
        "name":  "دۆشەكی ئەلیگرۆ150*2",
        "ID":  50,
        "Item_type":  ""
    },
    {
        "brand":  "",
        "name":  "دۆشەكی ئەلیگرۆ160*2",
        "ID":  51,
        "Item_type":  ""
    },
    {
        "brand":  "",
        "name":  "دۆشەكی ئەلیگرۆ180*2",
        "ID":  52,
        "Item_type":  ""
    },
    {
        "brand":  "",
        "name":  "دۆشەكی ئەلیگرۆ2*2",
        "ID":  53,
        "Item_type":  ""
    },
    {
        "brand":  "",
        "name":  "دۆشەكی ئاڕتیمس160*2",
        "ID":  55,
        "Item_type":  ""
    },
    {
        "brand":  "",
        "name":  "دۆشەكی ئاڕتیمس180*2",
        "ID":  56,
        "Item_type":  ""
    },
    {
        "brand":  "",
        "name":  "دۆشەكی ئاڕتیمس2*2",
        "ID":  57,
        "Item_type":  ""
    },
    {
        "brand":  "",
        "name":  "دۆشەكی سیڤیلا كۆن 160*2",
        "ID":  58,
        "Item_type":  ""
    },
    {
        "brand":  "",
        "name":  "دۆشەكی سیڤیلا كۆن180*2",
        "ID":  59,
        "Item_type":  ""
    },
    {
        "brand":  "",
        "name":  "دۆشەكی برییز 160*2",
        "ID":  60,
        "Item_type":  ""
    },
    {
        "brand":  "",
        "name":  "دۆشەكی برییز180*2",
        "ID":  61,
        "Item_type":  ""
    },
    {
        "brand":  "",
        "name":  "دۆشەكی برییز 2*2",
        "ID":  62,
        "Item_type":  ""
    },
    {
        "brand":  "",
        "name":  "دۆشەكی میمۆزا90*190",
        "ID":  63,
        "Item_type":  ""
    },
    {
        "brand":  "",
        "name":  "دۆشەكی میمۆزا1*2",
        "ID":  64,
        "Item_type":  ""
    },
    {
        "brand":  "",
        "name":  "پوف ئینێرجی 90",
        "ID":  65,
        "Item_type":  ""
    },
    {
        "brand":  "",
        "name":  "پوف ئینێرجی 140",
        "ID":  66,
        "Item_type":  ""
    },
    {
        "brand":  "",
        "name":  "پوف چێستەر 90",
        "ID":  67,
        "Item_type":  ""
    },
    {
        "brand":  "",
        "name":  "پوف چێستەر 140",
        "ID":  68,
        "Item_type":  ""
    },
    {
        "brand":  "",
        "name":  "پوف ئاڕتیمس",
        "ID":  69,
        "Item_type":  ""
    },
    {
        "brand":  "",
        "name":  "پوف ئەلیگرۆ",
        "ID":  70,
        "Item_type":  ""
    },
    {
        "brand":  "",
        "name":  "پوف دایمۆند",
        "ID":  71,
        "Item_type":  ""
    },
    {
        "brand":  "",
        "name":  "پوف سیڤیلا",
        "ID":  72,
        "Item_type":  ""
    },
    {
        "brand":  "",
        "name":  "كۆمیدی ئاڕتیمس",
        "ID":  73,
        "Item_type":  ""
    },
    {
        "brand":  "",
        "name":  "كۆمیدی سیڤیلا",
        "ID":  74,
        "Item_type":  ""
    },
    {
        "brand":  "",
        "name":  "كۆمیدی ئەلیگرۆ",
        "ID":  75,
        "Item_type":  ""
    },
    {
        "brand":  "",
        "name":  "كۆمیدی دایمۆند",
        "ID":  76,
        "Item_type":  ""
    },
    {
        "brand":  "",
        "name":  "سێتی چێستەر 120 *2",
        "ID":  77,
        "Item_type":  ""
    },
    {
        "brand":  "",
        "name":  "سێتی چێستەر 160*2",
        "ID":  78,
        "Item_type":  ""
    },
    {
        "brand":  "",
        "name":  "سێتی چێستەر 180*2",
        "ID":  79,
        "Item_type":  ""
    },
    {
        "brand":  "",
        "name":  "سێتی چێستەر 2*2",
        "ID":  80,
        "Item_type":  ""
    },
    {
        "brand":  "",
        "name":  "سێتی چێستەرسادە 120 *2",
        "ID":  81,
        "Item_type":  ""
    },
    {
        "brand":  "",
        "name":  "سێتی چێستەر سادە 160*2",
        "ID":  82,
        "Item_type":  ""
    },
    {
        "brand":  "",
        "name":  "سێتی چێستەر سادە 180*2",
        "ID":  83,
        "Item_type":  ""
    },
    {
        "brand":  "",
        "name":  "سێتی چێستەرسادە 2*2",
        "ID":  84,
        "Item_type":  ""
    },
    {
        "brand":  "",
        "name":  "سێتی ستایل120*2",
        "ID":  85,
        "Item_type":  ""
    },
    {
        "brand":  "",
        "name":  "سێتی ستایل160*2",
        "ID":  86,
        "Item_type":  ""
    },
    {
        "brand":  "",
        "name":  "سێتی ستایل180*2",
        "ID":  87,
        "Item_type":  ""
    },
    {
        "brand":  "",
        "name":  "سێتی ستایل2*2",
        "ID":  88,
        "Item_type":  ""
    },
    {
        "brand":  "",
        "name":  "سێتی ستایل سادە 120 *2",
        "ID":  89,
        "Item_type":  ""
    },
    {
        "brand":  "",
        "name":  "سێتی ستایل سادە 160*2",
        "ID":  90,
        "Item_type":  ""
    },
    {
        "brand":  "",
        "name":  "سێتی ستایل سادە 180*2",
        "ID":  91,
        "Item_type":  ""
    },
    {
        "brand":  "",
        "name":  "سێتی ستایل سادە 2*2",
        "ID":  92,
        "Item_type":  ""
    },
    {
        "brand":  "",
        "name":  "سێتی ژادە 160*2",
        "ID":  93,
        "Item_type":  ""
    },
    {
        "brand":  "",
        "name":  "سێتی ژادە180*2",
        "ID":  94,
        "Item_type":  ""
    },
    {
        "brand":  "",
        "name":  "سێتی ئاڕتیمس 120*2",
        "ID":  95,
        "Item_type":  ""
    },
    {
        "brand":  "",
        "name":  "سێتی ئاڕتیمس 150*2",
        "ID":  96,
        "Item_type":  ""
    },
    {
        "brand":  "",
        "name":  "سێتی ئاڕتیمس 160*2",
        "ID":  97,
        "Item_type":  ""
    },
    {
        "brand":  "",
        "name":  "سێتی ئاڕتیمس 180*2",
        "ID":  98,
        "Item_type":  ""
    },
    {
        "brand":  "",
        "name":  "سێتی ئاڕتیمس 2*2",
        "ID":  99,
        "Item_type":  ""
    },
    {
        "brand":  "",
        "name":  "سێتی دایمۆند 120*2",
        "ID":  100,
        "Item_type":  ""
    },
    {
        "brand":  "",
        "name":  "سێتی دایمۆند 150*2",
        "ID":  101,
        "Item_type":  ""
    },
    {
        "brand":  "",
        "name":  "سێتی دایمۆند 160*2",
        "ID":  102,
        "Item_type":  ""
    },
    {
        "brand":  "",
        "name":  "سێتی دایمۆند 180*2",
        "ID":  103,
        "Item_type":  ""
    },
    {
        "brand":  "",
        "name":  "سێتی دایمۆند 2*2",
        "ID":  104,
        "Item_type":  ""
    },
    {
        "brand":  "",
        "name":  "سێتی سیڤیلا 120*2",
        "ID":  105,
        "Item_type":  ""
    },
    {
        "brand":  "",
        "name":  "سێتی سیڤیلا 150*2",
        "ID":  106,
        "Item_type":  ""
    },
    {
        "brand":  "",
        "name":  "سێتی سیڤیلا 160*2",
        "ID":  107,
        "Item_type":  ""
    },
    {
        "brand":  "",
        "name":  "سێتی سیڤیلا 180*2",
        "ID":  108,
        "Item_type":  ""
    },
    {
        "brand":  "",
        "name":  "سێتی سیڤیلا 2*2",
        "ID":  109,
        "Item_type":  ""
    },
    {
        "brand":  "",
        "name":  "سێتی ئەلیگۆ 120*2",
        "ID":  110,
        "Item_type":  ""
    },
    {
        "brand":  "",
        "name":  "سێتی ئەلیگرۆ 150*2",
        "ID":  111,
        "Item_type":  ""
    },
    {
        "brand":  "",
        "name":  "سێتی ئەلیگرۆ 160*2",
        "ID":  112,
        "Item_type":  ""
    },
    {
        "brand":  "",
        "name":  "سێتی ئەلیگرۆ 180*2",
        "ID":  113,
        "Item_type":  ""
    },
    {
        "brand":  "",
        "name":  "سێتی ئەلیگرۆ 2*2",
        "ID":  114,
        "Item_type":  ""
    },
    {
        "brand":  "",
        "name":  "سێتی بڕاون 160*2",
        "ID":  115,
        "Item_type":  ""
    },
    {
        "brand":  "",
        "name":  "سێتی بڕاون 180*2",
        "ID":  116,
        "Item_type":  ""
    },
    {
        "brand":  "",
        "name":  "سێتی لارا 160*2",
        "ID":  117,
        "Item_type":  ""
    },
    {
        "brand":  "",
        "name":  "سێتی لارا180*2",
        "ID":  118,
        "Item_type":  ""
    },
    {
        "brand":  "",
        "name":  "سێتی لارا2*2",
        "ID":  119,
        "Item_type":  ""
    },
    {
        "brand":  "",
        "name":  "سێتی لارا سادە 160*2",
        "ID":  120,
        "Item_type":  ""
    },
    {
        "brand":  "",
        "name":  "سێتی لارا سادە 180*2",
        "ID":  121,
        "Item_type":  ""
    },
    {
        "brand":  "",
        "name":  "سێتی لارا سادە 2*2",
        "ID":  122,
        "Item_type":  ""
    },
    {
        "brand":  "",
        "name":  "سێتی نینۆڤا 180*2",
        "ID":  123,
        "Item_type":  ""
    },
    {
        "brand":  "",
        "name":  "سێتی سورف 120*2",
        "ID":  124,
        "Item_type":  ""
    },
    {
        "brand":  "",
        "name":  "سێتی سورف 160*2",
        "ID":  125,
        "Item_type":  ""
    },
    {
        "brand":  "",
        "name":  "سێتی سورف 180*2",
        "ID":  126,
        "Item_type":  ""
    },
    {
        "brand":  "",
        "name":  "سێتی سورف 2*2",
        "ID":  127,
        "Item_type":  ""
    },
    {
        "brand":  "",
        "name":  "سێتی سورف سادە 120*2",
        "ID":  128,
        "Item_type":  ""
    },
    {
        "brand":  "",
        "name":  "سێتی سورف سادە 160*2",
        "ID":  129,
        "Item_type":  ""
    },
    {
        "brand":  "",
        "name":  "سێتی سورف سادە 180*2",
        "ID":  130,
        "Item_type":  ""
    },
    {
        "brand":  "",
        "name":  "سێتی سورف سادە 2*2",
        "ID":  131,
        "Item_type":  ""
    },
    {
        "brand":  "",
        "name":  "سێتی فۆكۆس 120*2",
        "ID":  132,
        "Item_type":  ""
    },
    {
        "brand":  "",
        "name":  "سێتی فۆكۆس 160*2",
        "ID":  133,
        "Item_type":  ""
    },
    {
        "brand":  "",
        "name":  "سێتی فۆكۆس 180*2",
        "ID":  134,
        "Item_type":  ""
    },
    {
        "brand":  "",
        "name":  "سێتی فۆكۆس 2*2",
        "ID":  135,
        "Item_type":  ""
    },
    {
        "brand":  "",
        "name":  "سێتی فۆكۆس سادە 120*2",
        "ID":  136,
        "Item_type":  ""
    },
    {
        "brand":  "",
        "name":  "سێتی فۆكۆس سادە 160*2",
        "ID":  137,
        "Item_type":  ""
    },
    {
        "brand":  "",
        "name":  "سێتی فۆكۆس سادە 180*2",
        "ID":  138,
        "Item_type":  ""
    },
    {
        "brand":  "",
        "name":  "سێتی فۆكۆس سادە 2*2",
        "ID":  139,
        "Item_type":  ""
    },
    {
        "brand":  "",
        "name":  "سێتی میلۆدی 160*2",
        "ID":  140,
        "Item_type":  ""
    },
    {
        "brand":  "",
        "name":  "سێتی میلۆدی 180*2",
        "ID":  141,
        "Item_type":  ""
    },
    {
        "brand":  "",
        "name":  "سێتی سەفیر 120*2",
        "ID":  142,
        "Item_type":  ""
    },
    {
        "brand":  "",
        "name":  "سێتی سەفیر 160*2",
        "ID":  143,
        "Item_type":  ""
    },
    {
        "brand":  "",
        "name":  "سێتی سەفیر 180*2",
        "ID":  144,
        "Item_type":  ""
    },
    {
        "brand":  "",
        "name":  "سێتی سەفیر 2*2",
        "ID":  145,
        "Item_type":  ""
    },
    {
        "brand":  "",
        "name":  "سێتی سەفیر سادە 120*2",
        "ID":  146,
        "Item_type":  ""
    },
    {
        "brand":  "",
        "name":  "سێتی سەفیر سادە 160*2",
        "ID":  147,
        "Item_type":  ""
    },
    {
        "brand":  "",
        "name":  "سێتی سەفیر سادە 180*2",
        "ID":  148,
        "Item_type":  ""
    },
    {
        "brand":  "",
        "name":  "سێتی سەفیر سادە 2*2",
        "ID":  149,
        "Item_type":  ""
    },
    {
        "brand":  "",
        "name":  "پشتی منداڵ 45*30*8",
        "ID":  150,
        "Item_type":  ""
    },
    {
        "brand":  "",
        "name":  "پشتی قاچ25*20*15",
        "ID":  151,
        "Item_type":  ""
    },
    {
        "brand":  "",
        "name":  "پشتی 67*33*12",
        "ID":  152,
        "Item_type":  ""
    },
    {
        "brand":  "",
        "name":  "پشتی 60*40*16",
        "ID":  153,
        "Item_type":  ""
    },
    {
        "brand":  "",
        "name":  "پشتی 56*48*11.5",
        "ID":  154,
        "Item_type":  ""
    },
    {
        "brand":  "",
        "name":  "پشتی 54*40*11",
        "ID":  155,
        "Item_type":  ""
    },
    {
        "brand":  "",
        "name":  "پشتی 60*30*10",
        "ID":  156,
        "Item_type":  ""
    },
    {
        "brand":  "",
        "name":  "پشتی 60*40*10",
        "ID":  157,
        "Item_type":  ""
    },
    {
        "brand":  "",
        "name":  "پشتی 60*43*11",
        "ID":  158,
        "Item_type":  ""
    },
    {
        "brand":  "",
        "name":  "پشتی 50*30*10",
        "ID":  159,
        "Item_type":  ""
    },
    {
        "brand":  "",
        "name":  "پشتی 46*30*10",
        "ID":  160,
        "Item_type":  ""
    },
    {
        "brand":  "",
        "name":  "پشتی 70*42*15",
        "ID":  161,
        "Item_type":  ""
    },
    {
        "brand":  "",
        "name":  "بەرگ بامبۆ 120*2",
        "ID":  162,
        "Item_type":  ""
    },
    {
        "brand":  "",
        "name":  "بەرگ بامبۆ 180*2",
        "ID":  163,
        "Item_type":  ""
    },
    {
        "brand":  "",
        "name":  "بەرگ بامبۆ 90*2",
        "ID":  164,
        "Item_type":  ""
    },
    {
        "brand":  "",
        "name":  "بەرگ سادە 90*2",
        "ID":  165,
        "Item_type":  ""
    },
    {
        "brand":  "",
        "name":  "بەرگ سادە 1*2",
        "ID":  166,
        "Item_type":  ""
    },
    {
        "brand":  "",
        "name":  "بەرگی پشتی بامبۆ",
        "ID":  167,
        "Item_type":  ""
    },
    {
        "brand":  "",
        "name":  "بەرگی پشتی جێڵ سارد",
        "ID":  168,
        "Item_type":  ""
    },
    {
        "brand":  "",
        "name":  "سێتی داستی 1*2",
        "ID":  169,
        "Item_type":  ""
    },
    {
        "brand":  "",
        "name":  "سێتی ستێلا90*190",
        "ID":  170,
        "Item_type":  ""
    },
    {
        "brand":  "",
        "name":  "سێتی رۆس180*2",
        "ID":  172,
        "Item_type":  ""
    },
    {
        "brand":  "",
        "name":  "سێتی ڕۆس 2*2",
        "ID":  176,
        "Item_type":  ""
    },
    {
        "brand":  "",
        "name":  "سێتی لۆفت 1*2",
        "ID":  177,
        "Item_type":  ""
    },
    {
        "brand":  "",
        "name":  "سێتی ڕۆس1*2",
        "ID":  187,
        "Item_type":  ""
    },
    {
        "brand":  "",
        "name":  "دۆشەكی مندالان 60*120",
        "ID":  188,
        "Item_type":  ""
    },
    {
        "brand":  "",
        "name":  "پێتی ماتمازێل 90*190",
        "ID":  189,
        "Item_type":  ""
    },
    {
        "brand":  "",
        "name":  "پێتی ماتمازێل 160*2",
        "ID":  190,
        "Item_type":  ""
    },
    {
        "brand":  "",
        "name":  "پێتی ماتمازێل180*2",
        "ID":  191,
        "Item_type":  ""
    },
    {
        "brand":  "",
        "name":  "دۆشەكی ڤیۆلێت 180*2",
        "ID":  192,
        "Item_type":  ""
    },
    {
        "brand":  "",
        "name":  "سێتی ڤیۆلێت 180*2",
        "ID":  193,
        "Item_type":  ""
    },
    {
        "brand":  "",
        "name":  "سێتی پلازا 180*2",
        "ID":  194,
        "Item_type":  ""
    },
    {
        "brand":  "",
        "name":  "سێتی پلازا 120*2",
        "ID":  195,
        "Item_type":  ""
    },
    {
        "brand":  "",
        "name":  "سێتی پلازا 160*2",
        "ID":  196,
        "Item_type":  ""
    },
    {
        "brand":  "",
        "name":  "سێتی پلازا 2*2",
        "ID":  197,
        "Item_type":  ""
    },
    {
        "brand":  "",
        "name":  "سێتی ئیفۆر 180*2",
        "ID":  198,
        "Item_type":  ""
    },
    {
        "brand":  "",
        "name":  "سێتی ئیفۆر 1*2",
        "ID":  199,
        "Item_type":  ""
    },
    {
        "brand":  "",
        "name":  "سێتی جۆكەر 90*190",
        "ID":  200,
        "Item_type":  ""
    },
    {
        "brand":  "",
        "name":  "سێتی جۆكەر 1*2",
        "ID":  201,
        "Item_type":  ""
    },
    {
        "brand":  "",
        "name":  "سێتی ڕۆیال1*2",
        "ID":  202,
        "Item_type":  ""
    },
    {
        "brand":  "",
        "name":  "سێتی ڕۆیال120*2",
        "ID":  203,
        "Item_type":  ""
    },
    {
        "brand":  "",
        "name":  "سێتی داستی 120*2",
        "ID":  204,
        "Item_type":  ""
    },
    {
        "brand":  "",
        "name":  "سێتی ڕۆس2*2",
        "ID":  205,
        "Item_type":  ""
    },
    {
        "brand":  "",
        "name":  "لێفە 155*215",
        "ID":  208,
        "Item_type":  ""
    },
    {
        "brand":  "",
        "name":  "لێفە 220*240",
        "ID":  209,
        "Item_type":  ""
    },
    {
        "brand":  "",
        "name":  "پشتی دوقەد",
        "ID":  210,
        "Item_type":  ""
    },
    {
        "brand":  "",
        "name":  "دۆشەكی دایمۆند120*2",
        "ID":  211,
        "Item_type":  ""
    },
    {
        "brand":  "",
        "name":  "دۆشەکی پاڕادایس ١٤٠*٢",
        "ID":  212,
        "Item_type":  ""
    },
    {
        "brand":  "",
        "name":  "دۆشەکی برییز١٤٠*٢",
        "ID":  213,
        "Item_type":  ""
    },
    {
        "brand":  "",
        "name":  "سێتی دیلوکس١٨٠*٢",
        "ID":  215,
        "Item_type":  ""
    },
    {
        "brand":  "",
        "name":  "دۆشەکی بێێرا١٨٠*٢",
        "ID":  216,
        "Item_type":  ""
    },
    {
        "brand":  "",
        "name":  "دۆشەکی برییز ١٢٠*٢",
        "ID":  217,
        "Item_type":  ""
    },
    {
        "brand":  "",
        "name":  "دۆشەکی ئەلیگرۆ١٤٠*2",
        "ID":  218,
        "Item_type":  ""
    },
    {
        "brand":  "",
        "name":  "سێتی پلاتین 2*2",
        "ID":  219,
        "Item_type":  ""
    },
    {
        "brand":  "",
        "name":  "پێتی ماتمازێل2*2",
        "ID":  220,
        "Item_type":  ""
    },
    {
        "brand":  "",
        "name":  "دۆشەكی بێتا140*2",
        "ID":  221,
        "Item_type":  ""
    },
    {
        "brand":  "",
        "name":  "سێتی لۆفت 140*2",
        "ID":  222,
        "Item_type":  ""
    },
    {
        "brand":  "",
        "name":  "دۆشەکی پاپاتیا٩٠*١٩٠",
        "ID":  223,
        "Item_type":  ""
    },
    {
        "brand":  "",
        "name":  "دۆشەکی پاپاتیا١٨٠*٢",
        "ID":  224,
        "Item_type":  ""
    },
    {
        "brand":  "",
        "name":  "دۆشەکی فرێش١٢٠*٢",
        "ID":  225,
        "Item_type":  ""
    },
    {
        "brand":  "",
        "name":  "دۆشەکی فرێش١٨٠*٢",
        "ID":  226,
        "Item_type":  ""
    },
    {
        "brand":  "",
        "name":  "دۆشەکی فرێش٩٠*١٩٠",
        "ID":  227,
        "Item_type":  ""
    },
    {
        "brand":  "",
        "name":  "دۆشەکی دریم ماستەر٩٠*١٩٠",
        "ID":  228,
        "Item_type":  ""
    },
    {
        "brand":  "",
        "name":  "دۆشەکی دریم ماستەر١٨٠*٢",
        "ID":  229,
        "Item_type":  ""
    },
    {
        "brand":  "",
        "name":  "دۆشەکی ئیکۆ٩٠*١٩٠",
        "ID":  230,
        "Item_type":  ""
    },
    {
        "brand":  "",
        "name":  "دۆشەکی ئیکۆ١٢٠*٢",
        "ID":  231,
        "Item_type":  ""
    },
    {
        "brand":  "",
        "name":  "دۆشەکی ئیکۆ١٨٠*٢",
        "ID":  232,
        "Item_type":  ""
    },
    {
        "brand":  "",
        "name":  "دۆشەکی لوکس٩٠*١٩٠",
        "ID":  233,
        "Item_type":  ""
    },
    {
        "brand":  "",
        "name":  "دۆشەکی بێگۆنیا١٨٠*٢",
        "ID":  236,
        "Item_type":  ""
    },
    {
        "brand":  "",
        "name":  "دۆشەکی پالمیە١٨٠*٢",
        "ID":  237,
        "Item_type":  ""
    },
    {
        "brand":  "",
        "name":  "دۆشەکی ئۆسکار١٨٠*٢",
        "ID":  238,
        "Item_type":  ""
    },
    {
        "brand":  "",
        "name":  "سێتی پلازا١*٢",
        "ID":  240,
        "Item_type":  ""
    },
    {
        "brand":  "",
        "name":  "سێتی رۆس١٤٠*٢",
        "ID":  241,
        "Item_type":  ""
    },
    {
        "brand":  "",
        "name":  "سێتی فرێش١٨٠*٢",
        "ID":  242,
        "Item_type":  ""
    },
    {
        "brand":  "",
        "name":  "سێتی فرێش١٢٠*٢",
        "ID":  245,
        "Item_type":  ""
    },
    {
        "brand":  "",
        "name":  "سێتی فرێش٩٠*١٩٠",
        "ID":  246,
        "Item_type":  ""
    },
    {
        "brand":  "",
        "name":  "سێتی دریم ماستەر٩٠*١٩٠",
        "ID":  247,
        "Item_type":  ""
    },
    {
        "brand":  "",
        "name":  "سێتی دریم ماستەر١٨٠*٢",
        "ID":  248,
        "Item_type":  ""
    },
    {
        "brand":  "",
        "name":  "سێتی لوکس٩٠*١٩٠",
        "ID":  249,
        "Item_type":  ""
    },
    {
        "brand":  "",
        "name":  "دۆشەکی فرێش١*٢",
        "ID":  250,
        "Item_type":  ""
    },
    {
        "brand":  "",
        "name":  "دۆشەکی فرێش١٤٠*٢",
        "ID":  251,
        "Item_type":  ""
    },
    {
        "brand":  "",
        "name":  "دۆشەکی فرێش١٥٠*٢",
        "ID":  252,
        "Item_type":  ""
    },
    {
        "brand":  "",
        "name":  "دۆشەکی فرێش١٦٠*٢",
        "ID":  253,
        "Item_type":  ""
    },
    {
        "brand":  "",
        "name":  "دۆشەکی دریم ماستەر١٦٠*٢",
        "ID":  254,
        "Item_type":  ""
    },
    {
        "brand":  "",
        "name":  "دۆشەکی مارا١٦٠*٢",
        "ID":  255,
        "Item_type":  ""
    },
    {
        "brand":  "",
        "name":  "دۆشەکی مارا١٨٠*٢",
        "ID":  256,
        "Item_type":  ""
    },
    {
        "brand":  "",
        "name":  "دۆشەکی گراند دیلوکس١٨٠*٢",
        "ID":  257,
        "Item_type":  ""
    },
    {
        "brand":  "",
        "name":  "دۆشەکی کوینلاند١٦٠*٢",
        "ID":  258,
        "Item_type":  ""
    },
    {
        "brand":  "",
        "name":  "دۆشەکی کوینلاند١٨٠*٢",
        "ID":  259,
        "Item_type":  ""
    },
    {
        "brand":  "",
        "name":  "دۆشەکی گرۆسۆ١٨٠*٢",
        "ID":  260,
        "Item_type":  ""
    },
    {
        "brand":  "",
        "name":  "سێتی دریم ماستەر١٦٠*٢",
        "ID":  261,
        "Item_type":  ""
    },
    {
        "brand":  "",
        "name":  "سێتی مارا١٦٠*٢",
        "ID":  262,
        "Item_type":  ""
    },
    {
        "brand":  "",
        "name":  "سێتی مارا١٨٠*٢",
        "ID":  263,
        "Item_type":  ""
    },
    {
        "brand":  "",
        "name":  "سێتی گراندیلوکس١٨٠*٢",
        "ID":  264,
        "Item_type":  ""
    },
    {
        "brand":  "",
        "name":  "سێتی کوینلاند١٦٠*٢",
        "ID":  265,
        "Item_type":  ""
    },
    {
        "brand":  "",
        "name":  "سێتی کوینلاند١٨٠*٢",
        "ID":  266,
        "Item_type":  ""
    },
    {
        "brand":  "",
        "name":  "بەرگ بامبوو١٦٠*٢",
        "ID":  267,
        "Item_type":  ""
    },
    {
        "brand":  "",
        "name":  "بەرگ بامبۆ ٢*٢",
        "ID":  268,
        "Item_type":  ""
    },
    {
        "brand":  "",
        "name":  "دۆشەکی پاڕادایس١٤٠*٢",
        "ID":  270,
        "Item_type":  ""
    },
    {
        "brand":  "",
        "name":  "سێتی فلاوەر١٦٠*٢",
        "ID":  271,
        "Item_type":  ""
    },
    {
        "brand":  "",
        "name":  "سێتی چێستەر دەستی دوو ١٨٠*٢",
        "ID":  272,
        "Item_type":  ""
    },
    {
        "brand":  "",
        "name":  "بەرگی سادەی کۆن ١٨٠*٢",
        "ID":  273,
        "Item_type":  ""
    },
    {
        "brand":  "",
        "name":  "سێتی لۆفت ٩٠*١٩٠",
        "ID":  274,
        "Item_type":  ""
    },
    {
        "brand":  "",
        "name":  "لێفەی کۆنەکان",
        "ID":  275,
        "Item_type":  ""
    },
    {
        "brand":  "",
        "name":  "بەرگی سادە٩٠*١٩٠",
        "ID":  276,
        "Item_type":  ""
    },
    {
        "brand":  "",
        "name":  "پشتی کۆنی مل",
        "ID":  277,
        "Item_type":  ""
    },
    {
        "brand":  "",
        "name":  "دۆشەکی بێتا١٩٠*٢",
        "ID":  278,
        "Item_type":  ""
    },
    {
        "brand":  "",
        "name":  "دۆشەکی ئەلیگرۆ١٤٠*٢",
        "ID":  279,
        "Item_type":  ""
    },
    {
        "brand":  "",
        "name":  "دۆشەکی دریم ماستەر ١٥٠*٢",
        "ID":  280,
        "Item_type":  ""
    },
    {
        "brand":  "",
        "name":  "دۆشەکی دریم ماستەر ١*٢",
        "ID":  281,
        "Item_type":  ""
    },
    {
        "brand":  "",
        "name":  "دۆشەکی دریم ماستەر١٢٠*٢",
        "ID":  282,
        "Item_type":  ""
    },
    {
        "brand":  "",
        "name":  "دۆشەکی ئارڤین دیلوکس١٦٠*٢",
        "ID":  283,
        "Item_type":  ""
    },
    {
        "brand":  "",
        "name":  "دۆشەکی ئارڤین دیلوکس١٨٠*٢",
        "ID":  284,
        "Item_type":  ""
    },
    {
        "brand":  "",
        "name":  "دۆشەکی کۆمفی سلیپ١٦٠*٢",
        "ID":  285,
        "Item_type":  ""
    },
    {
        "brand":  "",
        "name":  "دۆشەکی کۆمفی سلیپ١٨٠*٢",
        "ID":  286,
        "Item_type":  ""
    },
    {
        "brand":  "",
        "name":  "دۆشەکی ئینفینیتی١٦٠*٢",
        "ID":  287,
        "Item_type":  ""
    },
    {
        "brand":  "",
        "name":  "دۆشەکی ئینفینیتی١٨٠*٢",
        "ID":  288,
        "Item_type":  ""
    },
    {
        "brand":  "",
        "name":  "دۆشەکی گۆلد کۆمفۆرت١٦٠*٢",
        "ID":  289,
        "Item_type":  ""
    },
    {
        "brand":  "",
        "name":  "دۆشەکی گۆلد کۆمفۆرت١٨٠*٢",
        "ID":  290,
        "Item_type":  ""
    },
    {
        "brand":  "",
        "name":  "دۆشەکی گراند دیلوکس١٦٠*٢",
        "ID":  293,
        "Item_type":  ""
    },
    {
        "brand":  "",
        "name":  "دۆشەکی گراند دیلوکس٢*٢",
        "ID":  294,
        "Item_type":  ""
    },
    {
        "brand":  "",
        "name":  "دۆشەکی ئەلیگرۆ٢*٢",
        "ID":  295,
        "Item_type":  ""
    },
    {
        "brand":  "",
        "name":  "سێتی ئارڤین دیلوکس١٨٠*٢",
        "ID":  296,
        "Item_type":  ""
    },
    {
        "brand":  "",
        "name":  "سێتی کۆمفی سلیپ١٨٠*٢",
        "ID":  297,
        "Item_type":  ""
    },
    {
        "brand":  "",
        "name":  "سێتی دریم ماستەر١٢٠*٢",
        "ID":  298,
        "Item_type":  ""
    },
    {
        "brand":  "",
        "name":  "سێتی دریم ماستەر١*٢",
        "ID":  299,
        "Item_type":  ""
    },
    {
        "brand":  "",
        "name":  "سێتی گراند دیلوکس١٦٠*٢",
        "ID":  300,
        "Item_type":  ""
    },
    {
        "brand":  "",
        "name":  "دۆشەکی ستایل١٨٠*٢",
        "ID":  301,
        "Item_type":  ""
    },
    {
        "brand":  "",
        "name":  "دۆشەکی دریم ماستەر ٩٠*٢",
        "ID":  302,
        "Item_type":  ""
    },
    {
        "brand":  "",
        "name":  "سێتی ئینفینیتی١٨٠*٢",
        "ID":  303,
        "Item_type":  ""
    },
    {
        "brand":  "",
        "name":  "دۆشەکی لوکس١٢٠*٢",
        "ID":  304,
        "Item_type":  ""
    },
    {
        "brand":  "",
        "name":  "دۆشەکی دریم ماستەر٢*٢",
        "ID":  305,
        "Item_type":  ""
    },
    {
        "brand":  "",
        "name":  "سێتی لوکس١٢٠*٢",
        "ID":  306,
        "Item_type":  ""
    },
    {
        "brand":  "",
        "name":  "دۆشەکی بێتریس١٨٠*٢",
        "ID":  307,
        "Item_type":  ""
    },
    {
        "brand":  "",
        "name":  "دۆشەکی دریم ماستەر١٤٠*٢",
        "ID":  308,
        "Item_type":  ""
    },
    {
        "brand":  "",
        "name":  "دۆشەکی گراند دیلوکس١٤٠*٢",
        "ID":  309,
        "Item_type":  ""
    },
    {
        "brand":  null,
        "name":  "دۆشەکی لینا ٩٠*١٩٠",
        "ID":  310,
        "Item_type":  null
    },
    {
        "brand":  null,
        "name":  "دۆشەکی ڕیلاکسی پێددار ١٦٠*٢",
        "ID":  311,
        "Item_type":  null
    },
    {
        "brand":  null,
        "name":  "دۆشەکی ڕیلاکسی پێددار ١٨٠*٢",
        "ID":  312,
        "Item_type":  null
    },
    {
        "brand":  null,
        "name":  "دۆشەکی ماتمازێل ١٨٠*٢",
        "ID":  313,
        "Item_type":  null
    },
    {
        "brand":  null,
        "name":  "دۆشەکی کوینلاند ١٥٠*٢",
        "ID":  314,
        "Item_type":  null
    },
    {
        "brand":  null,
        "name":  "سێتی پانژور ١٨٠*٢",
        "ID":  315,
        "Item_type":  null
    },
    {
        "brand":  null,
        "name":  "سێتی پانژور ١٦٠*٢",
        "ID":  316,
        "Item_type":  null
    },
    {
        "brand":  null,
        "name":  "سێتی هەپی گرەی ١٨٠*٢",
        "ID":  317,
        "Item_type":  null
    },
    {
        "brand":  null,
        "name":  "سێتی ساڵدا ١٨٠*٢",
        "ID":  318,
        "Item_type":  null
    },
    {
        "brand":  null,
        "name":  "دۆشەکی لەیدی ١*٢",
        "ID":  319,
        "Item_type":  null
    },
    {
        "brand":  null,
        "name":  "سێتی لەیدی١ *٢",
        "ID":  320,
        "Item_type":  null
    },
    {
        "brand":  null,
        "name":  "دۆشەکی گراندیلوکس ١*٢",
        "ID":  321,
        "Item_type":  null
    },
    {
        "brand":  null,
        "name":  "سێتی گراندیلوکس ١*٢",
        "ID":  322,
        "Item_type":  null
    },
    {
        "brand":  null,
        "name":  "بەرگ ڤیسکۆ ١٨٠*٢",
        "ID":  327,
        "Item_type":  null
    },
    {
        "brand":  null,
        "name":  "بەرگ ڤیسکۆ ١٢٠*٢",
        "ID":  328,
        "Item_type":  null
    },
    {
        "brand":  null,
        "name":  "بەرگ ڤیسکۆ ١*٢",
        "ID":  329,
        "Item_type":  null
    },
    {
        "brand":  null,
        "name":  "پشتی ڤیسکۆ ٥٤*٤٠*١١",
        "ID":  330,
        "Item_type":  null
    },
    {
        "brand":  null,
        "name":  "پشتی ڤیسکۆ ٦٠*٤٠*١٢",
        "ID":  331,
        "Item_type":  null
    },
    {
        "brand":  null,
        "name":  "پشتی ڤیسکۆ ٦٠*٤٠*١٣",
        "ID":  332,
        "Item_type":  null
    },
    {
        "brand":  null,
        "name":  "پشتی ڤیسکۆ ٧٠*٤٢*١٥",
        "ID":  333,
        "Item_type":  null
    },
    {
        "brand":  "",
        "name":  "پشتی ڤیسکۆ ٢٥*٢٠*١٠",
        "ID":  334,
        "Item_type":  ""
    },
    {
        "brand":  null,
        "name":  "سێتی کاربۆن ١٨٠*٢",
        "ID":  335,
        "Item_type":  null
    },
    {
        "brand":  null,
        "name":  "سێتی سپەیس ١٨٠*٢",
        "ID":  336,
        "Item_type":  null
    },
    {
        "brand":  null,
        "name":  "سێتی نیۆن ١٨٠*٢",
        "ID":  337,
        "Item_type":  null
    },
    {
        "brand":  null,
        "name":  "سێتی ماریسا ١٨٠*٢",
        "ID":  338,
        "Item_type":  null
    },
    {
        "brand":  null,
        "name":  "سێتی فوکێت ١٨٠*٢",
        "ID":  339,
        "Item_type":  null
    },
    {
        "brand":  null,
        "name":  "سێتی راڤیۆلی ١٨٠*٢",
        "ID":  340,
        "Item_type":  null
    },
    {
        "brand":  null,
        "name":  "سێتی ڕۆیاڵ ١٨٠*٢",
        "ID":  341,
        "Item_type":  null
    },
    {
        "brand":  "",
        "name":  "سێتی ئالێگرا ١٨٠*٢",
        "ID":  342,
        "Item_type":  ""
    },
    {
        "brand":  "",
        "name":  "دۆشەکی بامبوو لیف ١٨٠*٢",
        "ID":  343,
        "Item_type":  ""
    },
    {
        "brand":  null,
        "name":  "دۆشەکی بامبوو لیف ١٦٠*٢",
        "ID":  344,
        "Item_type":  null
    },
    {
        "brand":  null,
        "name":  "دۆشەکی سێرمۆ ریگولەیت ١٨٠*٢",
        "ID":  345,
        "Item_type":  null
    },
    {
        "brand":  null,
        "name":  "دۆشەکی سێرمۆ ریگولەیت ١٦٠*٢",
        "ID":  346,
        "Item_type":  null
    },
    {
        "brand":  null,
        "name":  "دۆشەکی سێرمۆ ریگولەیت ١٢٠*٢",
        "ID":  347,
        "Item_type":  null
    },
    {
        "brand":  null,
        "name":  "دۆشەکی نیۆن ١٨٠*٢",
        "ID":  348,
        "Item_type":  null
    },
    {
        "brand":  null,
        "name":  "دۆشەکی کاربۆن ١٨٠*٢",
        "ID":  349,
        "Item_type":  null
    },
    {
        "brand":  null,
        "name":  "دۆشەکی کاربۆن ١٦٠*٢",
        "ID":  352,
        "Item_type":  null
    },
    {
        "brand":  null,
        "name":  "دۆشەکی ئالێگرا ١٨٠*٢",
        "ID":  353,
        "Item_type":  null
    },
    {
        "brand":  null,
        "name":  "دۆشەکی ئالێگرا ١٦٠*٢",
        "ID":  354,
        "Item_type":  null
    },
    {
        "brand":  "",
        "name":  "دۆشەکی یۆرک ١٦٠*٢",
        "ID":  356,
        "Item_type":  ""
    },
    {
        "brand":  null,
        "name":  "دۆشەکی یۆرک ١٢٠*٢",
        "ID":  357,
        "Item_type":  null
    },
    {
        "brand":  null,
        "name":  "دۆشەکی کینگ ١٨٠*٢",
        "ID":  358,
        "Item_type":  null
    },
    {
        "brand":  null,
        "name":  "دۆشەکی کینگ ١٦٠*٢",
        "ID":  359,
        "Item_type":  null
    },
    {
        "brand":  null,
        "name":  "سێتی گراسۆ ١٨٠*٢",
        "ID":  360,
        "Item_type":  null
    },
    {
        "brand":  null,
        "name":  "دۆشەکی سێرمۆ ڕیگولەیت ١٥٠*٢",
        "ID":  362,
        "Item_type":  null
    },
    {
        "brand":  null,
        "name":  "دۆشەکی سێرمۆ ڕیگولەیت ٢*٢",
        "ID":  363,
        "Item_type":  null
    },
    {
        "brand":  null,
        "name":  "دۆشەکی کاسادە ١٨٠*٢",
        "ID":  364,
        "Item_type":  null
    },
    {
        "brand":  null,
        "name":  "دۆشەکی ڤیسکۆ نۆڤا پڵەس ١٦٠*٢",
        "ID":  365,
        "Item_type":  null
    },
    {
        "brand":  null,
        "name":  "دۆشەکی ڤیسکۆ نۆڤا پڵەس ١٨٠*٢",
        "ID":  366,
        "Item_type":  null
    },
    {
        "brand":  null,
        "name":  "دۆشەکی چارۆن ١٨٠*٢",
        "ID":  367,
        "Item_type":  null
    },
    {
        "brand":  null,
        "name":  "دۆشەکی دریم ٩٠*٢",
        "ID":  368,
        "Item_type":  null
    },
    {
        "brand":  null,
        "name":  "دۆشەکی دریم ١٨٠*٢",
        "ID":  369,
        "Item_type":  null
    },
    {
        "brand":  null,
        "name":  "دۆشەکی ئارتێ ٩٠*١٩٠",
        "ID":  370,
        "Item_type":  null
    },
    {
        "brand":  null,
        "name":  "دۆشەکی ئارتێ ١*٢",
        "ID":  371,
        "Item_type":  null
    },
    {
        "brand":  null,
        "name":  "دۆشەکی ئارتێ ١٢٠*٢",
        "ID":  372,
        "Item_type":  null
    },
    {
        "brand":  null,
        "name":  "دۆشەکی ئەمستەردام ١٦٠*٢",
        "ID":  373,
        "Item_type":  null
    },
    {
        "brand":  null,
        "name":  "دۆشەکی ئەمستەردام ١٨٠*٢",
        "ID":  374,
        "Item_type":  null
    },
    {
        "brand":  null,
        "name":  "دۆشەکی باڕۆک ١٨٠*٢",
        "ID":  375,
        "Item_type":  null
    },
    {
        "brand":  null,
        "name":  "تۆپەری لیڤی ٩٠*١٩٠",
        "ID":  376,
        "Item_type":  null
    },
    {
        "brand":  null,
        "name":  "دۆشەکی ساموا ١٢٠*٢",
        "ID":  377,
        "Item_type":  null
    },
    {
        "brand":  null,
        "name":  "دۆشەکی کاسادە ١٦٠*٢",
        "ID":  378,
        "Item_type":  null
    },
    {
        "brand":  null,
        "name":  "دۆشەکی دریم ١٦٠*٢",
        "ID":  379,
        "Item_type":  null
    },
    {
        "brand":  null,
        "name":  "سێتی ستارلایت ١٨٠*٢",
        "ID":  380,
        "Item_type":  null
    },
    {
        "brand":  null,
        "name":  "سێتی کاسادە   ١٨٠* ٢",
        "ID":  381,
        "Item_type":  null
    },
    {
        "brand":  null,
        "name":  "سێتی ئەلیزا  ١٦٠ * ٢",
        "ID":  382,
        "Item_type":  null
    },
    {
        "brand":  null,
        "name":  "سێتی ڕۆکۆ ١٦٠ * ٢",
        "ID":  383,
        "Item_type":  null
    },
    {
        "brand":  null,
        "name":  "سێتی هایبێرد  ١٨٠ * ٢",
        "ID":  384,
        "Item_type":  null
    },
    {
        "brand":  null,
        "name":  "سێتی سۆفتەج ١٦٠ * ٢",
        "ID":  385,
        "Item_type":  null
    },
    {
        "brand":  null,
        "name":  "سێتی سۆفتەج ١٨٠ * ٢",
        "ID":  386,
        "Item_type":  null
    },
    {
        "brand":  null,
        "name":  "سێتی ئەمستردام ١٨٠ *٢",
        "ID":  387,
        "Item_type":  null
    },
    {
        "brand":  null,
        "name":  "سێتی باڕۆک ١٦٠ * ٢",
        "ID":  388,
        "Item_type":  null
    },
    {
        "brand":  null,
        "name":  "سێتی باڕۆک ١٨٠ * ٢",
        "ID":  389,
        "Item_type":  null
    },
    {
        "brand":  null,
        "name":  "کۆمەدی ڕۆیاڵ",
        "ID":  390,
        "Item_type":  null
    },
    {
        "brand":  null,
        "name":  "پشتی ڤیسکۆ  L  ٧٠  * ٤٢ * ١٥ ",
        "ID":  391,
        "Item_type":  null
    },
    {
        "brand":  null,
        "name":  "پشتی ڤیسکۆ  L  ٦٠ *٤٠ * ١٣ ",
        "ID":  392,
        "Item_type":  null
    },
    {
        "brand":  null,
        "name":  "پشتی ڤیسکۆ  L  ٣٠ * ٢٨ * ١٢",
        "ID":  393,
        "Item_type":  null
    },
    {
        "brand":  null,
        "name":  "پستی ڤیسکۆ  L  ٥٦ * ٤٦ * ١١",
        "ID":  394,
        "Item_type":  null
    },
    {
        "brand":  null,
        "name":  "پشتی ڤیسکۆ  L  ٥٠ * ٣٠ *١٠",
        "ID":  395,
        "Item_type":  null
    },
    {
        "brand":  null,
        "name":  "پشتی ڤیسکۆ  L  ٥٠ * ٣٢ * ٦",
        "ID":  396,
        "Item_type":  null
    },
    {
        "brand":  null,
        "name":  "پشتی ڤیسکۆ  L  ٦٠ * ٣٨ * ١٠ ",
        "ID":  397,
        "Item_type":  null
    },
    {
        "brand":  null,
        "name":  "پشتی ڤیسکۆ  L  ٦٠ * ٤٠ * ١٢ ",
        "ID":  398,
        "Item_type":  null
    },
    {
        "brand":  null,
        "name":  "پشتی ڤیسکۆ  L  ٥٤ * ٤٠ * ١١ ",
        "ID":  399,
        "Item_type":  null
    },
    {
        "brand":  null,
        "name":  "پشتی ڤیسکۆ  L  ٢٥ * ٢٠ * ١٥ ",
        "ID":  401,
        "Item_type":  null
    },
    {
        "brand":  null,
        "name":  "فرۆشراوى پشتى فیسکۆ   L",
        "ID":  403,
        "Item_type":  null
    },
    {
        "brand":  null,
        "name":  "سێتی تۆکیۆ ١٨٠*٢",
        "ID":  404,
        "Item_type":  null
    },
    {
        "brand":  null,
        "name":  "سێتی سێرمۆ کەلەر ٢*٢",
        "ID":  405,
        "Item_type":  null
    },
    {
        "brand":  null,
        "name":  "سێتی کلاودس ١٨٠*٢",
        "ID":  406,
        "Item_type":  null
    },
    {
        "brand":  null,
        "name":  "سێتی ئەلیزا ١*٢",
        "ID":  407,
        "Item_type":  null
    },
    {
        "brand":  null,
        "name":  "سێتی ئەلیزا ١٢٠*٢",
        "ID":  408,
        "Item_type":  null
    },
    {
        "brand":  null,
        "name":  "سێتی ئەلیزا ٢*٢",
        "ID":  409,
        "Item_type":  null
    },
    {
        "brand":  null,
        "name":  "سێتی ئالێگرا ١*٢",
        "ID":  410,
        "Item_type":  null
    },
    {
        "brand":  null,
        "name":  "سێتی ئالێگرا ١٢٠*٢",
        "ID":  411,
        "Item_type":  null
    },
    {
        "brand":  null,
        "name":  "سێتی ئالێگرا ٢*٢",
        "ID":  412,
        "Item_type":  null
    },
    {
        "brand":  null,
        "name":  "سێتی ئۆپتیمەم ١*٢",
        "ID":  413,
        "Item_type":  null
    },
    {
        "brand":  null,
        "name":  "سێتی ئۆپتیمەم ١٢٠*٢",
        "ID":  414,
        "Item_type":  null
    },
    {
        "brand":  null,
        "name":  "دۆشەکی ساموا ٩٠*٢",
        "ID":  415,
        "Item_type":  null
    },
    {
        "brand":  "",
        "name":  "دۆشەکی ئینفنیتی ئارمیس ٩٠*١٩٠",
        "ID":  416,
        "Item_type":  ""
    },
    {
        "brand":  "",
        "name":  "دۆشەکی ئینفنیتی ئارمیس ٩٠*٢",
        "ID":  417,
        "Item_type":  ""
    },
    {
        "brand":  "",
        "name":  "دۆشەکی ئینفنیتی ئارمیس ١٢٠*٢",
        "ID":  418,
        "Item_type":  ""
    },
    {
        "brand":  null,
        "name":  "دۆشەکی ئینفنیتی ئارمیس ١٦٠*٢",
        "ID":  419,
        "Item_type":  null
    },
    {
        "brand":  null,
        "name":  "دۆشەکی ئینفنیتی ئارمیس ١٨٠*٢",
        "ID":  420,
        "Item_type":  null
    },
    {
        "brand":  null,
        "name":  "دۆشەکی کلاودس ١٨٠*٢",
        "ID":  421,
        "Item_type":  null
    },
    {
        "brand":  null,
        "name":  "دۆشەکی هێرمس ١٨٠*٢",
        "ID":  422,
        "Item_type":  null
    },
    {
        "brand":  null,
        "name":  "دۆشەکی هێرمس ٢*٢",
        "ID":  423,
        "Item_type":  null
    },
    {
        "brand":  null,
        "name":  "دۆشەکی بامبوو لیف ٢*٢",
        "ID":  424,
        "Item_type":  null
    },
    {
        "brand":  null,
        "name":  "دۆشەکی سێرمۆ ٩٠*١٩٠",
        "ID":  425,
        "Item_type":  null
    },
    {
        "brand":  null,
        "name":  "دۆشەکی سێرمۆ ١*٢",
        "ID":  426,
        "Item_type":  null
    },
    {
        "brand":  null,
        "name":  "دۆشەکی فلێکس فیت ٩٠*١٩٠",
        "ID":  427,
        "Item_type":  null
    },
    {
        "brand":  null,
        "name":  "دۆشەکی فلێکس فیت ١٢٠*٢",
        "ID":  428,
        "Item_type":  null
    },
    {
        "brand":  null,
        "name":  "دۆشەکی هارمۆنی ١٨٠*٢",
        "ID":  429,
        "Item_type":  null
    },
    {
        "brand":  null,
        "name":  "دۆشەکی سێرمۆ کەلەر ١٨٠*٢",
        "ID":  430,
        "Item_type":  null
    },
    {
        "brand":  null,
        "name":  "دۆشەکی ئایۆنیک ئینێرجی ٢*٢",
        "ID":  432,
        "Item_type":  null
    },
    {
        "brand":  null,
        "name":  "دۆشەکی ئۆپتیمەم ٩٠*١٩٠",
        "ID":  433,
        "Item_type":  null
    },
    {
        "brand":  null,
        "name":  "دۆشەکی ئۆپتیمەم ٩٠*٢",
        "ID":  434,
        "Item_type":  null
    },
    {
        "brand":  null,
        "name":  "دۆشەکی لینین ئۆرگانیک ١٨٠*٢",
        "ID":  435,
        "Item_type":  null
    },
    {
        "brand":  null,
        "name":  "دۆشەکی تێسلا سێراپی ١٨٠*٢",
        "ID":  436,
        "Item_type":  null
    },
    {
        "brand":  null,
        "name":  "دۆشەکی سویس کوین ١٨٠*٢",
        "ID":  437,
        "Item_type":  null
    },
    {
        "brand":  null,
        "name":  "دۆشەکی کوول تەچ ١٨٠*٢",
        "ID":  438,
        "Item_type":  null
    },
    {
        "brand":  null,
        "name":  "دۆشەکی کووڵ تەچ ١٦٠*٢",
        "ID":  439,
        "Item_type":  null
    },
    {
        "brand":  null,
        "name":  "دۆشەکی سویس کوین ١٦٠*٢",
        "ID":  440,
        "Item_type":  null
    },
    {
        "brand":  null,
        "name":  "دۆشەکی جۆی ١*٢",
        "ID":  441,
        "Item_type":  null
    },
    {
        "brand":  null,
        "name":  "دۆشەکی ماکس سلیپ ١*٢",
        "ID":  442,
        "Item_type":  null
    },
    {
        "brand":  null,
        "name":  "دۆشەکی فلێکس فیت ١٨٠*٢",
        "ID":  443,
        "Item_type":  null
    },
    {
        "brand":  null,
        "name":  "دۆشەکی کلاودس ١٦٠*٢",
        "ID":  444,
        "Item_type":  null
    },
    {
        "brand":  null,
        "name":  "دۆشەکی فلێکس فیت ١٦٠*٢",
        "ID":  445,
        "Item_type":  null
    },
    {
        "brand":  null,
        "name":  "دۆشەکی کلاودس ٢*٢",
        "ID":  446,
        "Item_type":  null
    },
    {
        "brand":  null,
        "name":  "دۆشەکی فلێکس فیت ١*٢",
        "ID":  447,
        "Item_type":  null
    },
    {
        "brand":  null,
        "name":  "دۆشەکی هێرمس ١٦٠*٢",
        "ID":  448,
        "Item_type":  null
    },
    {
        "brand":  null,
        "name":  "دۆشەکی تێسلا سێراپی ١٦٠*٢",
        "ID":  449,
        "Item_type":  null
    },
    {
        "brand":  null,
        "name":  "دۆشەکی کووڵ تەچ ١*٢",
        "ID":  450,
        "Item_type":  null
    },
    {
        "brand":  null,
        "name":  "دۆشەکی کووڵ تەچ ١٢٠*٢",
        "ID":  452,
        "Item_type":  null
    },
    {
        "brand":  null,
        "name":  "دۆشەکی کووڵ تەچ ٢*٢",
        "ID":  453,
        "Item_type":  null
    },
    {
        "brand":  null,
        "name":  "دۆشەکی لینین ئۆرگانیک ١٦٠*٢",
        "ID":  454,
        "Item_type":  null
    },
    {
        "brand":  null,
        "name":  "دۆشەکی سویس کوین ٢*٢",
        "ID":  455,
        "Item_type":  null
    },
    {
        "brand":  "",
        "name":  "دۆشەکی ویناڕت ١٨٠*٢",
        "ID":  456,
        "Item_type":  ""
    },
    {
        "brand":  null,
        "name":  "دۆشەکی لومینا ١٨٠*٢",
        "ID":  457,
        "Item_type":  null
    },
    {
        "brand":  "",
        "name":  "دۆشەکی ڤیسکۆی بێد ئاند سلیپ ١٨٠*٢",
        "ID":  458,
        "Item_type":  ""
    },
    {
        "brand":  null,
        "name":  "دۆشەکی ئەلۆڤێرا ١٨٠*٢",
        "ID":  459,
        "Item_type":  null
    },
    {
        "brand":  null,
        "name":  "دۆشەکی ویناڕت ١٦٠*٢",
        "ID":  460,
        "Item_type":  null
    },
    {
        "brand":  null,
        "name":  "دۆشەکی سیرێنا ١٦٠*٢",
        "ID":  461,
        "Item_type":  null
    },
    {
        "brand":  null,
        "name":  "دۆشەکی گرافایت پڵەس ١٨٠*٢",
        "ID":  462,
        "Item_type":  null
    },
    {
        "brand":  null,
        "name":  "دۆشەکی گرافایت پڵەس ١٦٠*٢",
        "ID":  463,
        "Item_type":  null
    },
    {
        "brand":  null,
        "name":  "دۆشەکی کرافت ١٨٠*٢",
        "ID":  464,
        "Item_type":  null
    },
    {
        "brand":  null,
        "name":  "دۆشەکی کرافت ١٦٠*٢",
        "ID":  465,
        "Item_type":  null
    },
    {
        "brand":  null,
        "name":  "دۆشەکی کاربۆن پڵەس ١٨٠*٢",
        "ID":  466,
        "Item_type":  null
    },
    {
        "brand":  null,
        "name":  "دۆشەکی نیو تۆسکانا ڤیسکۆ ١٨٠*٢",
        "ID":  467,
        "Item_type":  null
    },
    {
        "brand":  null,
        "name":  "دۆشەکی سێرمۆ ٩٠*٢",
        "ID":  468,
        "Item_type":  null
    },
    {
        "brand":  null,
        "name":  "دۆشەکی فلێکس فیت ٩٠*٢",
        "ID":  469,
        "Item_type":  null
    },
    {
        "brand":  null,
        "name":  "دۆشەکی بۆهیم ١٨٠*٢",
        "ID":  470,
        "Item_type":  null
    },
    {
        "brand":  null,
        "name":  "سێتی لینین ئۆرگانیک ١٨٠*٢",
        "ID":  471,
        "Item_type":  null
    },
    {
        "brand":  null,
        "name":  "سێتی بۆهیم ١٨٠*٢",
        "ID":  472,
        "Item_type":  null
    },
    {
        "brand":  null,
        "name":  "سێتی بۆهیم ١٦٠*٢",
        "ID":  473,
        "Item_type":  null
    },
    {
        "brand":  null,
        "name":  "سێتی بۆهیم ٢*٢",
        "ID":  474,
        "Item_type":  null
    },
    {
        "brand":  null,
        "name":  "سێتی کووڵ تەچ ١٨٠*٢",
        "ID":  475,
        "Item_type":  null
    },
    {
        "brand":  null,
        "name":  "سێتی ئالێگرا ماستەر ١٨٠*٢",
        "ID":  476,
        "Item_type":  null
    },
    {
        "brand":  null,
        "name":  "سێتی ئالێگرا ماستەر ١٦٠*٢",
        "ID":  477,
        "Item_type":  null
    },
    {
        "brand":  null,
        "name":  "سێتی سیرینا ١٦٠*٢",
        "ID":  478,
        "Item_type":  null
    },
    {
        "brand":  null,
        "name":  "سێتی کلاودس ١٦٠*٢",
        "ID":  479,
        "Item_type":  null
    },
    {
        "brand":  null,
        "name":  "سێتی ویناڕت ١٨٠*٢",
        "ID":  480,
        "Item_type":  null
    },
    {
        "brand":  null,
        "name":  "سێتی ویناڕت ١٦٠*٢",
        "ID":  481,
        "Item_type":  null
    },
    {
        "brand":  null,
        "name":  "سێتی سویس کوین ١٨٠*٢",
        "ID":  482,
        "Item_type":  null
    },
    {
        "brand":  null,
        "name":  "دۆشەکی باڕۆک پڵەس ٢*٢",
        "ID":  483,
        "Item_type":  null
    },
    {
        "brand":  null,
        "name":  "دۆشەکی تێسلا سێراپی ٢*٢",
        "ID":  484,
        "Item_type":  null
    },
    {
        "brand":  null,
        "name":  "دۆشەکی کاسادە ٢*٢",
        "ID":  485,
        "Item_type":  null
    },
    {
        "brand":  "",
        "name":  "پشتی ڤیسکۆ  L ٥٤*٤٠*١٢",
        "ID":  486,
        "Item_type":  ""
    },
    {
        "brand":  null,
        "name":  "پشتی ڤیسکۆ  L ٥٨*٤٦*١١.٥",
        "ID":  487,
        "Item_type":  null
    },
    {
        "brand":  null,
        "name":  "پشتی ڤیسکۆ  L ٦٠*٤٠*١٥",
        "ID":  488,
        "Item_type":  null
    },
    {
        "brand":  null,
        "name":  "پشتی ڤیسکۆ  L بەرگی لۆکە سێرێنیتی تەچ ٦٥*٤٣*١٢",
        "ID":  489,
        "Item_type":  null
    },
    {
        "brand":  "",
        "name":  "بەرگ ڤیسکۆ L ٢*٢",
        "ID":  490,
        "Item_type":  ""
    },
    {
        "brand":  null,
        "name":  "بەرگ ڤیسکۆ L پشتی ...٧٠*٥٠",
        "ID":  491,
        "Item_type":  null
    },
    {
        "brand":  "",
        "name":  "پشتی دانیشتنی ناو سەیارە/ژێر",
        "ID":  492,
        "Item_type":  ""
    },
    {
        "brand":  "",
        "name":  "پشتی دانیشتنی ناو سەیارە/پشت",
        "ID":  493,
        "Item_type":  ""
    },
    {
        "brand":  null,
        "name":  "بەرگ ڤیسکۆ L ١٦٠*٢",
        "ID":  494,
        "Item_type":  null
    }
]
